README.md
setup.py
bin/jcat
jcat/__init__.py
jcat.egg-info/PKG-INFO
jcat.egg-info/SOURCES.txt
jcat.egg-info/dependency_links.txt
jcat.egg-info/top_level.txt
jcat.egg-info/zip-safe