Metadata-Version: 2.1
Name: jcat
Version: 4
Summary: display json in flat format
Home-page: https://git.osuv.de/m/jcat
Author: Markus Bergholz
Author-email: markuman@gmail.com  
License: WTFPL
Platform: UNKNOWN
